pysha/__init__.py
pysha/auth.py
pysha/classes.py
pysha/colors.py
pysha/data_structures.py
pysha/decorators.py
pysha/enums.py
pysha/exceptions.py
pysha/functions.py
pysha/security.py
pysha/sign.py
pysha-0.1.3.1.dist-info/LICENSE
pysha-0.1.3.1.dist-info/METADATA
pysha-0.1.3.1.dist-info/WHEEL
pysha-0.1.3.1.dist-info/top_level.txt
pysha-0.1.3.1.dist-info/RECORD
