Metadata-Version: 2.1
Name: pysha
Version: 0.1.3.1
Summary: A New Born Python Framework That Helps You To Use Benefits Of Other Language With Some New Options.
Author-email: MrMegaExpert <1arhacker1@gmail.com>
License: GNU GENERAL PUBLIC LICENSE
Project-URL: Homepage, https://github.com/Arshiatmi/Pysha
Project-URL: Bug Tracker, https://github.com/Arshiatmi/Pysha/issues
Classifier: Programming Language :: Python :: 3
Classifier: License :: OSI Approved :: GNU General Public License v3 (GPLv3)
Classifier: Operating System :: OS Independent
Requires-Python: >=3.6
License-File: LICENSE
